Metadata-Version: 2.1
Name: pluspad
Version: 0.0.1
Summary: Following the create your own editor tutorial for quarantaine fun
Home-page: https://github.com/dicaso/pluspad
Author: Christophe Van Neste
Author-email: christophe.vanneste@kaust.edu.sa
License: MIT
Platform: UNKNOWN
Classifier: Programming Language :: Python :: 3
Classifier: License :: OSI Approved :: MIT License
Classifier: Operating System :: POSIX
Classifier: Development Status :: 1 - Planning
Requires-Python: >=3.6
Provides-Extra: documentation
